README.rst
setup.cfg
setup.py
py_steamcmd_installer/__init__.py
py_steamcmd_installer/py_steamcmd_installer.py
py_steamcmd_installer.egg-info/PKG-INFO
py_steamcmd_installer.egg-info/SOURCES.txt
py_steamcmd_installer.egg-info/dependency_links.txt
py_steamcmd_installer.egg-info/top_level.txt