Metadata-Version: 1.1
Name: py-steamcmd-installer
Version: 0.6.1
Summary: simple steamcmd app installer
Home-page: UNKNOWN
Author: Tobias Liese
Author-email: tobiasliese@hotmail.de
License: MIT
Keywords: steamcmd steamapp development
Platform: UNKNOWN
Classifier: Development Status :: 4 - Beta
Classifier: Intended Audience :: Developers
Classifier: Topic :: Software Development :: Libraries :: Python Modules
Classifier: License :: OSI Approved :: MIT License
Classifier: Programming Language :: Python :: 3
Classifier: Programming Language :: Python :: 3.3
Classifier: Programming Language :: Python :: 3.4
Classifier: Programming Language :: Python :: 3.5
Classifier: Programming Language :: Python :: 3.6
